tangelokit/__init__.py
tangelokit/generate_data_structure.py
tangelokit/schema_validation.py
tangelokit/tangelokit.py
tangelokit/common/__init__.py
tangelokit/common/enums.py
tangelokit/validator/__init__.py
tangelokit/validator/schema_validation.py
tangelokit/validator/schemas.py
tangelokit-0.0.5.dist-info/DESCRIPTION.rst
tangelokit-0.0.5.dist-info/METADATA
tangelokit-0.0.5.dist-info/RECORD
tangelokit-0.0.5.dist-info/WHEEL
tangelokit-0.0.5.dist-info/metadata.json
tangelokit-0.0.5.dist-info/top_level.txt
test/__init__.py
test/test_generate_data_structure.py
