Metadata-Version: 2.0
Name: tangelokit
Version: 0.0.5
Summary: Library created to generate structured data from tangelo
Home-page: UNKNOWN
Author: Arnold Blandon
Author-email: arnold.blandon1@gmail.com
License: UNKNOWN
Keywords: python,tangelo,kit,data
Platform: UNKNOWN
Classifier: Development Status :: 1 - Planning
Classifier: Intended Audience :: Developers
Classifier: Programming Language :: Python :: 3
Classifier: Operating System :: Unix
Classifier: Operating System :: MacOS :: MacOS X
Classifier: Operating System :: Microsoft :: Windows
Requires-Dist: jsonschema (==4.0.0)
